[
  {
    "locationId": 0,
    "locationName": "DeadMines",
    "locationLevel": 2,
    "canLocationBeExplored": true,
    "locationDifficulty": "EASY",
    "locationStages": {
      "0": {
        "type": "LocationStageQuestGiver",
        "stageName": "Mine Outside campsite",
        "stageDiscovered": false,
        "itemsIdNeededToEnterStage": [],
        "questGiverId": 1
      },
      "1": {
        "type": "LocationStageCombat",
        "stageName": "Mine entry door",
        "stageDiscovered": false,
        "itemsIdNeededToEnterStage": [],
        "locationEnemyIdList": [
          205
        ]
      },
      "2": {
        "type": "LocationStageCombat",
        "stageName": "Miner's Quarters",
        "stageDiscovered": false,
        "itemsIdNeededToEnterStage": [],
        "locationEnemyIdList": [
          204
        ]
      },
      "3": {
        "type": "LocationStageFindItem",
        "stageName": "Miner's Quarters shelves",
        "stageDiscovered": false,
        "itemsIdNeededToEnterStage": [],
        "itemsId": [
          900,
          900,
          902,
          902
        ]
      },
      "4": {
        "type": "LocationStageCombat",
        "stageName": "Abandoned Tunnels",
        "stageDiscovered": false,
        "itemsIdNeededToEnterStage": [],
        "locationEnemyIdList": [
          204
        ]
      },
      "5": {
        "type": "LocationStageFindItem",
        "stageName": "Collapsed Chambers",
        "stageDiscovered": false,
        "itemsIdNeededToEnterStage": [],
        "itemsId": [
          608
        ]
      },
      "6": {
        "type": "LocationStageCombat",
        "stageName": "Abandoned Tunnels",
        "stageDiscovered": false,
        "itemsIdNeededToEnterStage": [],
        "locationEnemyIdList": [
          204
        ]
      },
      "7": {
        "type": "LocationStageFindItem",
        "stageName": "Collapsed Chambers",
        "stageDiscovered": false,
        "itemsIdNeededToEnterStage": [],
        "itemsId": [
          505
        ]
      },
      "8": {
        "type": "LocationStageFindItem",
        "stageName": "Ore Deposits",
        "stageDiscovered": false,
        "itemsIdNeededToEnterStage": [],
        "itemsId": [
          703,
          703
        ]
      },
      "9": {
        "type": "LocationStageCombat",
        "stageName": "Abandoned Tunnels",
        "stageDiscovered": false,
        "itemsIdNeededToEnterStage": [],
        "locationEnemyIdList": [
          204,
          204
        ]
      },
      "10": {
        "type": "LocationStageCombat",
        "stageName": "Refinery",
        "stageDiscovered": false,
        "itemsIdNeededToEnterStage": [],
        "locationEnemyIdList": [
          205,
          204,
          204
        ]
      },
      "11": {
        "type": "LocationStageFindItem",
        "stageName": "Ore storage",
        "stageDiscovered": false,
        "itemsIdNeededToEnterStage": [],
        "itemsId": [
          703,
          703,
          703,
          703
        ]
      },
      "12": {
        "type": "LocationStageCombat",
        "stageName": "Miner Leader Chamber",
        "stageDiscovered": false,
        "itemsIdNeededToEnterStage": [],
        "locationEnemyIdList": [
          208
        ]
      },
      "13": {
        "type": "LocationStageFindItem",
        "stageName": "Miner leader chamber locked chest",
        "stageDiscovered": false,
        "itemsIdNeededToEnterStage": [],
        "itemsId": [
          404,
          103,
          609
        ]
      }
    }
  },
  {
    "locationId": 1,
    "locationName": "Tower of Damned",
    "locationLevel": 2,
    "canLocationBeExplored": true,
    "locationDifficulty": "MEDIUM",
    "locationStages": {
      "0": {
        "type": "LocationStageCombat",
        "stageName": "Tower Door",
        "stageDiscovered": true,
        "itemsIdNeededToEnterStage": [
          103
        ],
        "locationEnemyIdList": [
          303
        ]
      },
      "1": {
        "type": "LocationStageCombat",
        "stageName": "Forgotten Crypts",
        "stageDiscovered": false,
        "itemsIdNeededToEnterStage": [],
        "locationEnemyIdList": [
          303,
          303
        ]
      },
      "2": {
        "type": "LocationStageFindItem",
        "stageName": "Cursed Altar",
        "stageDiscovered": false,
        "itemsIdNeededToEnterStage": [],
        "itemsId": [
          506,
          405
        ]
      },
      "3": {
        "type": "LocationStageUseItem",
        "stageName": "Empty Socket in Cursed Altar",
        "stageDiscovered": false,
        "itemsIdNeededToEnterStage": [],
        "itemsId": [
          106
        ]
      },
      "4": {
        "type": "LocationStageCombat",
        "stageName": "Sorrowful Chapel",
        "stageDiscovered": false,
        "itemsIdNeededToEnterStage": [],
        "locationEnemyIdList": [
          304
        ]
      },
      "5": {
        "type": "LocationStageFindItem",
        "stageName": "Spectral Library",
        "stageDiscovered": false,
        "itemsIdNeededToEnterStage": [],
        "itemsId": [
          104,
          306
        ]
      },
      "6": {
        "type": "LocationStageCombat",
        "stageName": "Malevolent Throne Room",
        "stageDiscovered": false,
        "itemsIdNeededToEnterStage": [],
        "locationEnemyIdList": [
          209
        ]
      },
      "7": {
        "type": "LocationStageFindItem",
        "stageName": "Necromancer Hidden Chest",
        "stageDiscovered": false,
        "itemsIdNeededToEnterStage": [],
        "itemsId": [
          212,
          211
        ]
      }
    }
  },
  {
    "locationId": 2,
    "locationName": "Crystal Lake",
    "locationLevel": 1,
    "canLocationBeExplored": true,
    "locationDifficulty": "EASY",
    "locationStages": {
      "0": {
        "type": "LocationStageQuestGiver",
        "stageName": "Fisherman Cabin",
        "stageDiscovered": true,
        "itemsIdNeededToEnterStage": [],
        "questGiverId": 2
      },
      "1": {
        "type": "LocationStageCombat",
        "stageName": "Lake shore",
        "stageDiscovered": false,
        "itemsIdNeededToEnterStage": [],
        "locationEnemyIdList": [
          401
        ]
      },
      "2": {
        "type": "LocationStageCombat",
        "stageName": "Lake shore",
        "stageDiscovered": false,
        "itemsIdNeededToEnterStage": [],
        "locationEnemyIdList": [
          401
        ]
      },
      "3": {
        "type": "LocationStageCombat",
        "stageName": "Old fishing pier",
        "stageDiscovered": false,
        "itemsIdNeededToEnterStage": [],
        "locationEnemyIdList": [
          401,
          401
        ]
      },
      "4": {
        "type": "LocationStageFindItem",
        "stageName": "The End of Old fishing pier",
        "stageDiscovered": false,
        "itemsIdNeededToEnterStage": [],
        "itemsId": [
          301,
          900,
          902,
          1003,
          1003,
          1002
        ]
      },
      "5": {
        "type": "LocationStageCombat",
        "stageName": "Lake Isle",
        "stageDiscovered": false,
        "itemsIdNeededToEnterStage": [],
        "locationEnemyIdList": [
          401,
          402
        ]
      }
    }
  },
  {
    "locationId": 3,
    "locationName": "Bear Cave",
    "locationLevel": 2,
    "canLocationBeExplored": true,
    "locationDifficulty": "MEDIUM",
    "locationStages": {
      "0": {
        "type": "LocationStageCombat",
        "stageName": "Bear cave chamber",
        "stageDiscovered": true,
        "itemsIdNeededToEnterStage": [],
        "locationEnemyIdList": [
          401,
          401
        ]
      },
      "1": {
        "type": "LocationStageFindItem",
        "stageName": "Human Corpse",
        "stageDiscovered": false,
        "itemsIdNeededToEnterStage": [],
        "itemsId": [
          106
        ]
      },
      "2": {
        "type": "LocationStageQuestGiver",
        "stageName": "Letter lying next to corpse",
        "stageDiscovered": false,
        "itemsIdNeededToEnterStage": [],
        "questGiverId": 1
      }
    }
  },
  {
    "locationId": 4,
    "locationName": "Mystic Hollow",
    "locationLevel": 1,
    "canLocationBeExplored": true,
    "locationDifficulty": "EASY",
    "locationStages": {
      "0": {
        "type": "LocationStageNothingOutcome",
        "stageName": "Main gate City Guard",
        "stageDiscovered": true,
        "itemsIdNeededToEnterStage": []
      },
      "1": {
        "type": "LocationStageBlacksmith",
        "stageName": "Blacksmith Equipment",
        "stageDiscovered": false,
        "itemsIdNeededToEnterStage": []
      },
      "2": {
        "type": "LocationStageVendor",
        "stageName": "Blacksmith Equipment Merchant",
        "stageDiscovered": false,
        "itemsIdNeededToEnterStage": [],
        "vendorId": 0
      },
      "3": {
        "type": "LocationStageVendor",
        "stageName": "Ore Merchant",
        "stageDiscovered": false,
        "itemsIdNeededToEnterStage": [],
        "vendorId": 1
      },
      "4": {
        "type": "LocationStageVendor",
        "stageName": "Alchemist potion Vendor",
        "stageDiscovered": false,
        "itemsIdNeededToEnterStage": [],
        "vendorId": 2
      },
      "5": {
        "type": "LocationStageVendor",
        "stageName": "Alchemist reagent Vendor",
        "stageDiscovered": false,
        "itemsIdNeededToEnterStage": [],
        "vendorId": 4
      },
      "6": {
        "type": "LocationStageVendor",
        "stageName": "Merchant of Trinkets",
        "stageDiscovered": false,
        "itemsIdNeededToEnterStage": [],
        "vendorId": 3
      },
      "7": {
        "type": "LocationStagePlaceToRest",
        "stageName": "Empty house",
        "stageDiscovered": false,
        "itemsIdNeededToEnterStage": [
          107
        ]
      },
      "8": {
        "type": "LocationStageVendor",
        "stageName": "Tavern Keeper",
        "stageDiscovered": false,
        "itemsIdNeededToEnterStage": [],
        "vendorId": 5
      },
      "9": {
        "type": "LocationStageQuestGiver",
        "stageName": "Man with cape in Tavern",
        "stageDiscovered": false,
        "itemsIdNeededToEnterStage": [],
        "questGiverId": 0
      },
      "10": {
        "type": "LocationStageCombat",
        "stageName": "Tavern Back door",
        "stageDiscovered": false,
        "itemsIdNeededToEnterStage": [],
        "locationEnemyIdList": [
          210,
          210,
          210
        ]
      }
    }
  }
]
